repzip/__init__.py
repzip/__main__.py
repzip-0.1.0.dist-info/LICENSE
repzip-0.1.0.dist-info/METADATA
repzip-0.1.0.dist-info/WHEEL
repzip-0.1.0.dist-info/entry_points.txt
repzip-0.1.0.dist-info/top_level.txt
repzip-0.1.0.dist-info/RECORD
