Metadata-Version: 2.1
Name: repzip
Version: 0.1.0
Summary: Reproducible zip build utility
Author-email: Ayowel <ayowel@users.noreply.github.com>
License: GNU GENERAL PUBLIC LICENSE
Project-URL: Homepage, https://github.com/ayowel/rzip
Project-URL: Issues, https://github.com/ayowel/rzip/issues
Classifier: Environment :: Console
Classifier: License :: OSI Approved :: GNU General Public License v3 (GPLv3)
Classifier: Operating System :: OS Independent
Classifier: Programming Language :: Python
Classifier: Programming Language :: Python :: 3
Classifier: Programming Language :: Python :: 3 :: Only
Classifier: Programming Language :: Python :: 3.9
Classifier: Programming Language :: Python :: 3.10
Classifier: Programming Language :: Python :: 3.11
Classifier: Programming Language :: Python :: 3.12
Classifier: Programming Language :: Python :: 3.13
Requires-Python: >=3.3
License-File: LICENSE
